statistic_tool/__init__.py
statistic_tool/feature.py
statistic_tool/sample.py
statistic_tool-0.0.3.dist-info/LICENSE
statistic_tool-0.0.3.dist-info/METADATA
statistic_tool-0.0.3.dist-info/WHEEL
statistic_tool-0.0.3.dist-info/top_level.txt
statistic_tool-0.0.3.dist-info/RECORD
